github_projects_automation/__init__.py
github_projects_automation/__main__.py
github_projects_automation/py.typed
github_projects_automation-0.0.1.dist-info/LICENSE
github_projects_automation-0.0.1.dist-info/METADATA
github_projects_automation-0.0.1.dist-info/WHEEL
github_projects_automation-0.0.1.dist-info/entry_points.txt
github_projects_automation-0.0.1.dist-info/RECORD
