Metadata-Version: 2.1
Name: github-projects-automation
Version: 0.0.1
Summary: Github Projects Automation
Home-page: https://github.com/NASA-IMPACT/github-projects-automation
License: MIT
Author: Ashish Acharya
Author-email: ashish.acharya14@gmail.com
Requires-Python: >=3.7,<4.0
Classifier: Development Status :: 1 - Planning
Classifier: License :: OSI Approved :: MIT License
Classifier: Programming Language :: Python :: 3
Classifier: Programming Language :: Python :: 3.7
Classifier: Programming Language :: Python :: 3.8
Classifier: Programming Language :: Python :: 3.9
Classifier: Programming Language :: Python :: 3.10
Classifier: Programming Language :: Python :: 3.11
Requires-Dist: click (>=8.0.1)
Project-URL: Changelog, https://github.com/NASA-IMPACT/github-projects-automation/releases
Project-URL: Documentation, https://github-projects-automation.readthedocs.io
Project-URL: Repository, https://github.com/NASA-IMPACT/github-projects-automation
